flapper/__init__.py
flapper/env.py
flapper/log.py
flapper/model.py
flapper-0.1.0.dist-info/METADATA
flapper-0.1.0.dist-info/WHEEL
flapper-0.1.0.dist-info/top_level.txt
flapper-0.1.0.dist-info/RECORD
