Metadata-Version: 2.2
Name: flapper
Version: 0.1.0
Requires-Dist: numpy
Requires-Dist: scipy
Requires-Dist: matplotlib
Requires-Dist: gym
Requires-Dist: imageio
Requires-Dist: torch
Requires-Dist: pandas
Dynamic: requires-dist
